odoo/addons/database_size/README.rst
odoo/addons/database_size/__init__.py
odoo/addons/database_size/__manifest__.py
odoo/addons/database_size/data/ir_cron_data.xml
odoo/addons/database_size/i18n/database_size.pot
odoo/addons/database_size/i18n/it.po
odoo/addons/database_size/models/__init__.py
odoo/addons/database_size/models/ir_model_index_size.py
odoo/addons/database_size/models/ir_model_relation_size.py
odoo/addons/database_size/models/ir_model_size.py
odoo/addons/database_size/models/res_config_settings.py
odoo/addons/database_size/readme/CONFIGURE.md
odoo/addons/database_size/readme/CONTRIBUTORS.md
odoo/addons/database_size/readme/DESCRIPTION.md
odoo/addons/database_size/readme/USAGE.md
odoo/addons/database_size/report/__init__.py
odoo/addons/database_size/report/ir_model_size_report.py
odoo/addons/database_size/report/ir_model_size_report_views.xml
odoo/addons/database_size/security/ir.model.access.csv
odoo/addons/database_size/static/description/icon.png
odoo/addons/database_size/static/description/index.html
odoo/addons/database_size/static/images/compare_model_size.png
odoo/addons/database_size/static/images/model_size.png
odoo/addons/database_size/static/images/select_date.png
odoo/addons/database_size/static/src/scss/list_view_wrap_header.scss
odoo/addons/database_size/tests/__init__.py
odoo/addons/database_size/tests/test_database_size.py
odoo/addons/database_size/views/ir_model_size_views.xml
odoo/addons/database_size/views/res_config_settings_views.xml
odoo_addon_database_size-18.0.1.0.2.dist-info/METADATA
odoo_addon_database_size-18.0.1.0.2.dist-info/WHEEL
odoo_addon_database_size-18.0.1.0.2.dist-info/top_level.txt
odoo_addon_database_size-18.0.1.0.2.dist-info/RECORD
