Metadata-Version: 2.1
Name: odoo-addon-database_size
Version: 18.0.1.0.2
Requires-Python: >=3.10
Requires-Dist: odoo==18.0.*
Summary: Database Size
Home-page: https://github.com/OCA/server-tools
License: AGPL-3
Author: Opener B.V.,Odoo Community Association (OCA)
Author-email: support@odoo-community.org
Classifier: Programming Language :: Python
Classifier: Framework :: Odoo
Classifier: Framework :: Odoo :: 18.0
Classifier: License :: OSI Approved :: GNU Affero General Public License v3
